kostsample
