Metadata-Version: 2.1
Name: kostsample
Version: 1.0.2
Summary: python-sample-app is a starter template for new python applications
Home-page: https://github.com/becosta/python-sample-app
Author: Benjamin Costa & Vitalii Kostyreva
Author-email: kostyreva-09876@gmail.com
License: MIT
Platform: UNKNOWN
